python_versionning-1.3.1.dist-info/METADATA
python_versionning-1.3.1.dist-info/RECORD
python_versionning-1.3.1.dist-info/WHEEL
python_versionning-1.3.1.dist-info/entry_points.txt
python_versionning-1.3.1.dist-info/top_level.txt
pyver/__init__.py
pyver/__main__.py
pyver/commands.py
pyver/parse.py
