Metadata-Version: 2.1
Name: python-versionning
Version: 1.3.1
Summary: Manage your projects' version
Home-page: https://github.com/Afoucaul/pyver
Author: Armand Foucault
Author-email: armand.foucault@telecom-bretagne.eu
License: UNKNOWN
Platform: UNKNOWN
